nodespecs-0.1.9.dist-info/licenses/LICENSE
specs/__init__.py
specs/__main__.py
specs/benchmark.py
specs/cmd.py
specs/cpuinfo.py
specs/hardware.py
specs/pyinfo.py
specs/communicate/__init__.py
specs/communicate/aboutme.py
specs/communicate/tcpsocket.py
specs/communicate/tcpip/__init__.py
specs/communicate/tcpip/client.py
specs/communicate/tcpip/server.py
specs/communicate/upload/__init__.py
specs/disk/__init__.py
specs/disk/automate.py
specs/disk/drive.py
nodespecs-0.1.9.dist-info/METADATA
nodespecs-0.1.9.dist-info/WHEEL
nodespecs-0.1.9.dist-info/entry_points.txt
nodespecs-0.1.9.dist-info/top_level.txt
nodespecs-0.1.9.dist-info/RECORD
