Metadata-Version: 2.4
Name: nodespecs
Version: 0.1.9
Summary: The specs summarize utilities for computer instance
Author-email: jinsanity <jinsanityff@gmail.com>
License: The MIT License (MIT)
Project-URL: Homepage, https://github.com/jinsanity07git/nodespecs
Keywords: cpu,gpu,benchmark
Classifier: License :: OSI Approved :: MIT License
Classifier: Programming Language :: Python
Classifier: Programming Language :: Python :: 3
Requires-Python: >=3.6
License-File: LICENSE
Requires-Dist: tabulate>=0.8.0
Provides-Extra: dev
Requires-Dist: GPUtil; extra == "dev"
Requires-Dist: pip-tools; extra == "dev"
Requires-Dist: psutil>=5.9.5; extra == "dev"
Requires-Dist: toml; extra == "dev"
Dynamic: license-file
